{
  "fetch_time": "2026-07-10 03:18:24",
  "fetch_timestamp": 1783649904.384673,
  "match_count": 3,
  "matches": [
    {
      "match_id": 2040466,
      "match_num": "周五098",
      "match_date": "2026-07-11",
      "match_time": "03:00:00",
      "home_team": "西班牙",
      "away_team": "比利时",
      "home_team_full": "西班牙",
      "away_team_full": "比利时",
      "league_name": "世界杯",
      "match_status": "Selling",
      "remark": "比赛将在美国-加利福尼亚州英格尔伍德举行",
      "score_odds": {
        "update_date": "2026-07-10",
        "update_time": "09:46:38",
        "scores": {
          "0:0": "14.00",
          "0:1": "14.23",
          "0:2": "34.44",
          "0:3": "98.27",
          "0:4": "328.04",
          "0:5": "803.13",
          "1:0": "7.75",
          "1:1": "8.27",
          "1:2": "13.38",
          "1:3": "45.63",
          "1:4": "132.86",
          "1:5": "536.57",
          "2:0": "7.37",
          "2:1": "6.52",
          "2:2": "12.00",
          "2:3": "35.45",
          "2:4": "100.0",
          "2:5": "436.35",
          "3:0": "12.07",
          "3:1": "10.71",
          "3:2": "15.42",
          "3:3": "35.18",
          "4:0": "29.20",
          "4:1": "28.91",
          "4:2": "43.87",
          "5:0": "76.86",
          "5:1": "76.39",
          "5:2": "88.63",
          "胜其他": "33.18",
          "平其他": "165.80",
          "负其他": "150.0"
        }
      }
    },
    {
      "match_id": 2040459,
      "match_num": "周六099",
      "match_date": "2026-07-12",
      "match_time": "05:00:00",
      "home_team": "挪威",
      "away_team": "英格兰",
      "home_team_full": "挪威",
      "away_team_full": "英格兰",
      "league_name": "世界杯",
      "match_status": "Selling",
      "remark": "比赛将在美国-佛罗里达州迈阿密加登斯举行",
      "score_odds": {
        "update_date": "2026-07-09",
        "update_time": "17:30:52",
        "scores": {
          "0:0": "15.12",
          "0:1": "9.45",
          "0:2": "7.99",
          "0:3": "17.00",
          "0:4": "38.94",
          "0:5": "102.53",
          "1:0": "14.00",
          "1:1": "6.85",
          "1:2": "6.50",
          "1:3": "13.48",
          "1:4": "28.45",
          "1:5": "84.60",
          "2:0": "24.32",
          "2:1": "9.21",
          "2:2": "8.81",
          "2:3": "18.41",
          "2:4": "48.76",
          "2:5": "138.78",
          "3:0": "60.00",
          "3:1": "28.00",
          "3:2": "25.00",
          "3:3": "40.00",
          "4:0": "203.30",
          "4:1": "110.04",
          "4:2": "101.39",
          "5:0": "500.0",
          "5:1": "437.77",
          "5:2": "432.24",
          "胜其他": "125.0",
          "平其他": "200.0",
          "负其他": "45.00"
        }
      }
    },
    {
      "match_id": 2040467,
      "match_num": "周六100",
      "match_date": "2026-07-12",
      "match_time": "09:00:00",
      "home_team": "阿根廷",
      "away_team": "瑞士",
      "home_team_full": "阿根廷",
      "away_team_full": "瑞士",
      "league_name": "世界杯",
      "match_status": "Selling",
      "remark": "比赛将在美国-密苏里州堪萨斯城举行",
      "score_odds": {
        "update_date": "2026-07-09",
        "update_time": "18:51:34",
        "scores": {
          "0:0": "8.50",
          "0:1": "12.21",
          "0:2": "30.27",
          "0:3": "98.11",
          "0:4": "443.55",
          "0:5": "1000",
          "1:0": "5.90",
          "1:1": "6.44",
          "1:2": "13.73",
          "1:3": "64.26",
          "1:4": "307.15",
          "1:5": "781.47",
          "2:0": "6.50",
          "2:1": "7.07",
          "2:2": "17.00",
          "2:3": "65.00",
          "2:4": "401.29",
          "2:5": "978.44",
          "3:0": "10.68",
          "3:1": "9.50",
          "3:2": "28.00",
          "3:3": "90.97",
          "4:0": "27.00",
          "4:1": "35.00",
          "4:2": "80.00",
          "5:0": "88.00",
          "5:1": "114.19",
          "5:2": "256.81",
          "胜其他": "70.00",
          "平其他": "400.0",
          "负其他": "400.0"
        }
      }
    }
  ]
}